odoo/addons/product_label_format_restrict/README.rst
odoo/addons/product_label_format_restrict/__init__.py
odoo/addons/product_label_format_restrict/__manifest__.py
odoo/addons/product_label_format_restrict/models/__init__.py
odoo/addons/product_label_format_restrict/models/res_company.py
odoo/addons/product_label_format_restrict/models/res_config_settings.py
odoo/addons/product_label_format_restrict/readme/CONFIGURE.md
odoo/addons/product_label_format_restrict/readme/CONTRIBUTORS.md
odoo/addons/product_label_format_restrict/readme/DESCRIPTION.md
odoo/addons/product_label_format_restrict/static/description/icon.png
odoo/addons/product_label_format_restrict/static/description/index.html
odoo/addons/product_label_format_restrict/views/res_config_settings_views.xml
odoo/addons/product_label_format_restrict/wizards/__init__.py
odoo/addons/product_label_format_restrict/wizards/product_label_layout.py
odoo_addon_product_label_format_restrict-17.0.1.0.0.1.dist-info/METADATA
odoo_addon_product_label_format_restrict-17.0.1.0.0.1.dist-info/WHEEL
odoo_addon_product_label_format_restrict-17.0.1.0.0.1.dist-info/top_level.txt
odoo_addon_product_label_format_restrict-17.0.1.0.0.1.dist-info/RECORD
